LICENSE
hydralette/__init__.py
hydralette/hydralette.py
hydralette-0.2.4.dist-info/LICENSE
hydralette-0.2.4.dist-info/METADATA
hydralette-0.2.4.dist-info/WHEEL
hydralette-0.2.4.dist-info/RECORD
