Metadata-Version: 2.1
Name: hydralette
Version: 0.2.4
Summary: 
Home-page: https://github.com/ValeKnappich/hydralette
License: MIT
Keywords: config,cfg,hydra
Author: ValeKnappich
Requires-Python: >=3.10,<4.0
Classifier: License :: OSI Approved :: MIT License
Classifier: Programming Language :: Python :: 3
Classifier: Programming Language :: Python :: 3.10
Classifier: Programming Language :: Python :: 3.11
Requires-Dist: dill (>=0.3.7,<0.4.0)
Requires-Dist: pyyaml (>=6.0.1,<7.0.0)
Project-URL: Repository, https://github.com/ValeKnappich/hydralette
